memory.v
`timescale 1ns / 1ps
//////////////////////////////////////////////////////////////////////////////////
// Company: 
// Engineer: 
// 
// Create Date:    13:02:46 04/28/2021 
// Design Name: 
// Module Name:    memory 
// Project Name: 
// Target Devices: 
// Tool versions: 
// Description: 
//
// Dependencies: 
//
// Revision: 
// Revision 0.01 - File Created
// Additional Comments: 
//
//////////////////////////////////////////////////////////////////////////////////
module memory(
    input [31:0] data,
    input [15:0] add,
    input mrd,mwr,rst,clk,
    output reg [31:0] mdata
    );


reg [31:0] mem [15:0];

always @(posedge clk)
begin

      if(rst)
		  begin
		  
		  mdata<=32'd0;
		  
		  end 
     else if(mwr) // load 
	     
		    mem[add]<=data;
	  
	  else if(mrd) // fetch 
	  
	       mdata <= mem[add];
	  
	  
end 

   

endmodule

arithmetic_logic_unit.v
`timescale 1ns / 1ps
//////////////////////////////////////////////////////////////////////////////////
// Company: 
// Engineer: 
// 
// Create Date:    02:30:01 05/21/2021 
// Design Name: 
// Module Name:    arithmetic_logic_unit 
// Project Name: 
// Target Devices: 
// Tool versions: 
// Description: 
//
// Dependencies: 
//
// Revision: 
// Revision 0.01 - File Created
// Additional Comments: 
//
//////////////////////////////////////////////////////////////////////////////////
module arithmetic_logic_unit(
    input start,
    input [31:0] acout,
	 input [31:0] B_in,
    input [2:0] opcode,
    input clk,rst,
    output reg [31:0]  alout
    
    );
	 
	 reg [5:0]ad;
	
	 
	 reg [5:0]temp;
	 
	 always@(posedge clk)
	
	 begin		
	           if (rst && !start )
				     begin
				  			
		           	alout <= 32'd0;
                 
                   end 						
     	       else  
			   begin
				
				   case({opcode})
				
				     3'b000:  begin alout <= 32'b0; end
				     3'b001:  begin
					              temp <= B_in[0]+B_in[1]+B_in[2]+B_in[3]+B_in[4]+
									          B_in[5]+B_in[6]+B_in[7]+B_in[8]+B_in[9]+
												 B_in[10]+B_in[11]+B_in[12]+B_in[13]+B_in[14]+
												 B_in[15]+B_in[16]+B_in[17]+B_in[18]+B_in[19]+
												 B_in[20]+B_in[21]+B_in[22]+B_in[23]+B_in[24]+
												 B_in[25]+B_in[26]+B_in[27]+B_in[28]+B_in[29]+
												 B_in[30]+B_in[31];
									   
                               case(temp)
                               
                                   
                               6'd0  : alout<=32'h00000000;
										 6'd1  : alout<=32'h00000001;
										 6'd2  : alout<=32'h00000003;
										 6'd3  : alout<=32'h00000007;
										 6'd4  : alout<=32'h0000000f;
										 6'd5  : alout<=32'h0000001f;
										 6'd6  : alout<=32'h0000003f;
										 6'd7  : alout<=32'h0000007f;
										 6'd8  : alout<=32'h000000ff;
										 6'd9  : alout<=32'h000001ff;
										 6'd10 : alout<=32'h000003ff;
										 6'd11 : alout<=32'h000007ff;
										 6'd12 : alout<=32'h00000fff;
										 6'd13 : alout<=32'h00001fff;
										 6'd14 : alout<=32'h00003fff;
										 6'd15 : alout<=32'h00007fff;
										 6'd16 : alout<=32'h0000ffff;
										 6'd17 : alout<=32'h0001ffff;
										 6'd18 : alout<=32'h0003ffff;
										 6'd19 : alout<=32'h0007ffff;
										 6'd20 : alout<=32'h000fffff;
										 6'd21 : alout<=32'h001fffff;
										 6'd22 : alout<=32'h003fffff;
										 6'd23 : alout<=32'h007fffff;
										 6'd24 : alout<=32'h00ffffff;
										 6'd25 : alout<=32'h01ffffff;
										 6'd26 : alout<=32'h03ffffff;
										 6'd27 : alout<=32'h07ffffff;
										 6'd28 : alout<=32'h0fffffff;
										 6'd29 : alout<=32'h1fffffff;
										 6'd29 : alout<=32'h3fffffff;
										 6'd30 : alout<=32'h7fffffff;
										 6'd31 : alout<=32'hffffffff;
                               							
										  
										  
										  
										  
										  endcase										  
												 
									
									end
    								
				     3'b010: begin  alout <= acout + B_in; end
				     3'b011: begin  alout <= acout - B_in; end
				     3'b100: begin  alout <= acout | B_in; end
				     3'b101: begin  alout <= acout & B_in; end
				     3'b110: begin  alout <= acout ^ B_in; end
				     3'b111: begin alout <= alout; end  // store example 
					  
					  
					  // jump =101
				
					endcase
				
				end
			
			
	 
	 
end
endmodule

accumulator.v
`timescale 1ns / 1ps
//////////////////////////////////////////////////////////////////////////////////
// Company: 
// Engineer: 
// 
// Create Date:    07:10:07 04/27/2021 
// Design Name: 
// Module Name:    accumulator 
// Project Name: 
// Target Devices: 
// Tool versions: 
// Description: 
//
// Dependencies: 
//
// Revision: 
// Revision 0.01 - File Created
// Additional Comments: 
//
//////////////////////////////////////////////////////////////////////////////////
module accumulator(
    input [31:0] alout,
	 input [31:0]A,
    input clk,ldac,rst,
	 input Asel,
    output reg [31:0] acout
    );
always@ (posedge clk)
begin
if (rst)
begin
	acout <= 32'd0;
end
	
else if (ldac  && !rst) 
begin
	acout <= Asel ? alout : A;
end
end

endmodule

instruction_register.v
`timescale 1ns / 1ps
//////////////////////////////////////////////////////////////////////////////////
// Company: 
// Engineer: 
// 
// Create Date:    05:14:16 04/27/2021 
// Design Name: 
// Module Name:    instruction_register 
// Project Name: 
// Target Devices: 
// Tool versions: 
// Description: 
//
// Dependencies: 
//
// Revision: 
// Revision 0.01 - File Created
// Additional Comments: 
//
//////////////////////////////////////////////////////////////////////////////////
module instruction_register(
    input [15:0] mdat,
    input clk,ldir,rst,
    output reg [15:3] adir,
    output reg [2:0] opcode
    );
always @(posedge clk)
begin
if (rst)
begin
 adir <= 5'b00000;
 opcode <= 3'b000;
end

else if (!rst && ldir)
begin
 adir <= mdat[15:3];
 opcode <= mdat[2:0];
end

end

endmodule

program_counter.v
`timescale 1ns / 1ps
//////////////////////////////////////////////////////////////////////////////////
// Company: 
// Engineer: 
// 
// Create Date:    19:59:37 05/23/2021 
// Design Name: 
// Module Name:    program_counter 
// Project Name: 
// Target Devices: 
// Tool versions: 
// Description: 
//
// Dependencies: 
//
// Revision: 
// Revision 0.01 - File Created
// Additional Comments: 
//
//////////////////////////////////////////////////////////////////////////////////
module program_counter(
    input pclk,rst,ld_pc,inc_pc,
    output reg [4:0] adpc
    );

	//wire mdat;
	

	
	always@ (posedge pclk)
	begin
	
	         if (rst && !ld_pc)
		
	        		adpc <= 5'b00000;
		
		
			      else
					  begin
					     if(inc_pc)
						    adpc<=adpc+1'b1;
						  else
						    adpc<=adpc;
						  
						   
				    end 
	end

endmodule

decoder.v
`timescale 1ns / 1ps
//////////////////////////////////////////////////////////////////////////////////
// Company: 
// Engineer: 
// 
// Create Date:    00:46:05 05/25/2021 
// Design Name: 
// Module Name:    decoder 
// Project Name: 
// Target Devices: 
// Tool versions: 
// Description: 
//
// Dependencies: 
//
// Revision: 
// Revision 0.01 - File Created
// Additional Comments: 
//
//////////////////////////////////////////////////////////////////////////////////
module decoder(
    input clk ,rst,
    output reg MRd,ld_pc,Inc_pc,ld_IR,Ld_acc,ALU_setup,Mwr
    );
	 
	 
	 
// fetch , load ,execute ,store 	 
	 
	 reg [2:0]count;
	 
	 always@ (posedge clk)
	 begin
	        if(rst)
              begin
				       count<=1'b0;
				  end 
            				
	         else
               begin
                    count<=count+1'b1;
                       case (count)
							   3'b001 : begin MRd<=1'b1;
								               ld_pc<=1'b0;
													Inc_pc<=1'b0;
													ld_IR<=1'b0;
													Ld_acc<=1'b0;
													ALU_setup<=1'b0;
													Mwr<=1'b0;
							              end
								3'b010 : begin MRd<=1'b0;
								               ld_pc<=1'b1;
													Inc_pc<=1'b0;
													ld_IR<=1'b0;
													Ld_acc<=1'b0;
													ALU_setup<=1'b0;
													Mwr<=1'b0;
							              end			  
											  
								3'b011 : begin MRd<=1'b0;
								               ld_pc<=1'b0;
													Inc_pc<=1'b1;
													ld_IR<=1'b0;
													Ld_acc<=1'b0;
													ALU_setup<=1'b0;
													Mwr<=1'b0;
							              end			 			  
											  
								3'b100 : begin MRd<=1'b0;
								               ld_pc<=1'b0;
													Inc_pc<=1'b0;
													ld_IR<=1'b1;
													Ld_acc<=1'b0;
													ALU_setup<=1'b0;
													Mwr<=1'b0;
							              end			 			  
								3'b101 : begin MRd<=1'b0;
								               ld_pc<=1'b0;
													Inc_pc<=1'b0;
													ld_IR<=1'b0;
													Ld_acc<=1'b1;
													ALU_setup<=1'b0;
													Mwr<=1'b0;
							              end			 
                        3'b110 : begin MRd<=1'b0;
								               ld_pc<=1'b0;
													Inc_pc<=1'b0;
													ld_IR<=1'b0;
													Ld_acc<=1'b0;
													ALU_setup<=1'b1;
													Mwr<=1'b0;
							              end			 											  
                        3'b111 : begin MRd<=1'b0;
								               ld_pc<=1'b0;
													Inc_pc<=1'b0;
													ld_IR<=1'b0;
													Ld_acc<=1'b0;
													ALU_setup<=1'b0;
													Mwr<=1'b1;
							              end		
											  
							endcase				  
											  
               end 					
	 
	                 
	 
	 end


endmodule

RISC.v
`timescale 1ns / 1ps
//////////////////////////////////////////////////////////////////////////////////
// Company: 
// Engineer: 
// 
// Create Date:    14:52:57 06/04/2021 
// Design Name: 
// Module Name:    RISC 
// Project Name: 
// Target Devices: 
// Tool versions: 
// Description: 
//
// Dependencies: 
//
// Revision: 
// Revision 0.01 - File Created
// Additional Comments: 
//
//////////////////////////////////////////////////////////////////////////////////
module RISC ( input [31:0]A,B,input Asel,input [15:0]add ,input clk,rst, output [31:0]mdata, output [4:0] adpc
    );


wire [15:3] adir;
wire [2:0] opcode;

wire [31:0] acout;
wire  [31:0]  alout;

wire mrd,ld_pc,inc_pc,ld_IR,ldac,ALU_setup,mwr;


decoder                 d1 (clk ,rst,mrd,ld_pc,inc_pc,ld_IR,ldac,ALU_setup,mwr );
	 

program_counter        d2(clk,rst,ld_pc,inc_pc, adpc); 

instruction_register   d3( add, clk,ld_IR,rst,adir, opcode);


accumulator            d4( alout,A,clk,ldac,rst,Asel,acout);

arithmetic_logic_unit  d5 (ALU_setup,acout,B, opcode, clk,rst,alout);

memory                 d6 (alout,add,mrd,mwr,rst,clk, mdata);


endmodule

RISC_TB.v
`timescale 1ns / 1ps

////////////////////////////////////////////////////////////////////////////////
// Company: 
// Engineer:
//
// Create Date:   09:29:13 06/05/2021
// Design Name:   RISC
// Module Name:   C:/Users/HOME/Desktop/projects VLSI O/major_project_programs/major_project_programs/RISC_TB.v
// Project Name:  major_project_programs
// Target Device:  
// Tool versions:  
// Description: 
//
// Verilog Test Fixture created by ISE for module: RISC
//
// Dependencies:
// 
// Revision:
// Revision 0.01 - File Created
// Additional Comments:
// 
////////////////////////////////////////////////////////////////////////////////

module RISC_TB;

	// Inputs
	reg [31:0] A;
	reg [31:0] B;
	reg Asel;
	reg [15:0] add;
	reg clk;
	reg rst;

	// Outputs
	wire [31:0] mdata;

	// Instantiate the Unit Under Test (UUT)
	RISC uut (
		.A(A), 
		.B(B), 
		.Asel(Asel), 
		.add(add), 
		.clk(clk), 
		.rst(rst), 
		.mdata(mdata)
	);

	initial begin
		// Initialize Inputs
		A = 0;
		B = 0;
		Asel = 0;
		add = 0;
		clk = 0;
		rst = 1;

		// Wait 100 ns for global reset to finish
		#20 rst=0;
		
		#10 A = 32'd12; B = 32'd14 ; Asel = 0 ;add = 3;
		#10 A = 32'd10; B = 32'd14 ; Asel = 0 ;add = 3;
		#10 A = 32'd15; B = 32'd14 ; Asel = 0 ;add = 3;
		#10 A = 32'd17; B = 32'd14 ; Asel = 0 ;add = 3;
		
		#10 A = 32'd12; B = 32'd14 ; Asel = 0 ;add = 3;
		#10 A = 32'd10; B = 32'd14 ; Asel = 0 ;add = 3;
		#10 A = 32'd15; B = 32'd14 ; Asel = 0 ;add = 3;
		#10 A = 32'd17; B = 32'd14 ; Asel = 0 ;add = 3;
		
        
		// Add stimulus here

	end
	
always #10 clk=~clk;	

initial begin


	$dumpfile ("RISC.vcd");
	$dumpvars (1,RISC_TB.uut);
	



end 



      
endmodule

RISC.vcd
$date
   Sat Jun 26 13:34:01 2021
$end
$version
  P.20131013
$end
$timescale
  1ps
$end
$scope module RISC_TB $end
$scope module uut $end
$var wire 1 ! A [31] $end
$var wire 1 " A [30] $end
$var wire 1 # A [29] $end
$var wire 1 $ A [28] $end
$var wire 1 % A [27] $end
$var wire 1 & A [26] $end
$var wire 1 ' A [25] $end
$var wire 1 ( A [24] $end
$var wire 1 ) A [23] $end
$var wire 1 * A [22] $end
$var wire 1 + A [21] $end
$var wire 1 , A [20] $end
$var wire 1 - A [19] $end
$var wire 1 . A [18] $end
$var wire 1 / A [17] $end
$var wire 1 0 A [16] $end
$var wire 1 1 A [15] $end
$var wire 1 2 A [14] $end
$var wire 1 3 A [13] $end
$var wire 1 4 A [12] $end
$var wire 1 5 A [11] $end
$var wire 1 6 A [10] $end
$var wire 1 7 A [9] $end
$var wire 1 8 A [8] $end
$var wire 1 9 A [7] $end
$var wire 1 : A [6] $end
$var wire 1 ; A [5] $end
$var wire 1 < A [4] $end
$var wire 1 = A [3] $end
$var wire 1 > A [2] $end
$var wire 1 ? A [1] $end
$var wire 1 @ A [0] $end
$var wire 1 A B [31] $end
$var wire 1 B B [30] $end
$var wire 1 C B [29] $end
$var wire 1 D B [28] $end
$var wire 1 E B [27] $end
$var wire 1 F B [26] $end
$var wire 1 G B [25] $end
$var wire 1 H B [24] $end
$var wire 1 I B [23] $end
$var wire 1 J B [22] $end
$var wire 1 K B [21] $end
$var wire 1 L B [20] $end
$var wire 1 M B [19] $end
$var wire 1 N B [18] $end
$var wire 1 O B [17] $end
$var wire 1 P B [16] $end
$var wire 1 Q B [15] $end
$var wire 1 R B [14] $end
$var wire 1 S B [13] $end
$var wire 1 T B [12] $end
$var wire 1 U B [11] $end
$var wire 1 V B [10] $end
$var wire 1 W B [9] $end
$var wire 1 X B [8] $end
$var wire 1 Y B [7] $end
$var wire 1 Z B [6] $end
$var wire 1 [ B [5] $end
$var wire 1 \ B [4] $end
$var wire 1 ] B [3] $end
$var wire 1 ^ B [2] $end
$var wire 1 _ B [1] $end
$var wire 1 ` B [0] $end
$var wire 1 a Asel $end
$var wire 1 b add [15] $end
$var wire 1 c add [14] $end
$var wire 1 d add [13] $end
$var wire 1 e add [12] $end
$var wire 1 f add [11] $end
$var wire 1 g add [10] $end
$var wire 1 h add [9] $end
$var wire 1 i add [8] $end
$var wire 1 j add [7] $end
$var wire 1 k add [6] $end
$var wire 1 l add [5] $end
$var wire 1 m add [4] $end
$var wire 1 n add [3] $end
$var wire 1 o add [2] $end
$var wire 1 p add [1] $end
$var wire 1 q add [0] $end
$var wire 1 r clk $end
$var wire 1 s rst $end
$var wire 1 t mdata [31] $end
$var wire 1 u mdata [30] $end
$var wire 1 v mdata [29] $end
$var wire 1 w mdata [28] $end
$var wire 1 x mdata [27] $end
$var wire 1 y mdata [26] $end
$var wire 1 z mdata [25] $end
$var wire 1 { mdata [24] $end
$var wire 1 | mdata [23] $end
$var wire 1 } mdata [22] $end
$var wire 1 ~ mdata [21] $end
$var wire 1 !! mdata [20] $end
$var wire 1 "! mdata [19] $end
$var wire 1 #! mdata [18] $end
$var wire 1 $! mdata [17] $end
$var wire 1 %! mdata [16] $end
$var wire 1 &! mdata [15] $end
$var wire 1 '! mdata [14] $end
$var wire 1 (! mdata [13] $end
$var wire 1 )! mdata [12] $end
$var wire 1 *! mdata [11] $end
$var wire 1 +! mdata [10] $end
$var wire 1 ,! mdata [9] $end
$var wire 1 -! mdata [8] $end
$var wire 1 .! mdata [7] $end
$var wire 1 /! mdata [6] $end
$var wire 1 0! mdata [5] $end
$var wire 1 1! mdata [4] $end
$var wire 1 2! mdata [3] $end
$var wire 1 3! mdata [2] $end
$var wire 1 4! mdata [1] $end
$var wire 1 5! mdata [0] $end
$var wire 1 6! adpc [4] $end
$var wire 1 7! adpc [3] $end
$var wire 1 8! adpc [2] $end
$var wire 1 9! adpc [1] $end
$var wire 1 :! adpc [0] $end
$var wire 1 ;! adir [15] $end
$var wire 1 <! adir [14] $end
$var wire 1 =! adir [13] $end
$var wire 1 >! adir [12] $end
$var wire 1 ?! adir [11] $end
$var wire 1 @! adir [10] $end
$var wire 1 A! adir [9] $end
$var wire 1 B! adir [8] $end
$var wire 1 C! adir [7] $end
$var wire 1 D! adir [6] $end
$var wire 1 E! adir [5] $end
$var wire 1 F! adir [4] $end
$var wire 1 G! adir [3] $end
$var wire 1 H! opcode [2] $end
$var wire 1 I! opcode [1] $end
$var wire 1 J! opcode [0] $end
$var wire 1 K! acout [31] $end
$var wire 1 L! acout [30] $end
$var wire 1 M! acout [29] $end
$var wire 1 N! acout [28] $end
$var wire 1 O! acout [27] $end
$var wire 1 P! acout [26] $end
$var wire 1 Q! acout [25] $end
$var wire 1 R! acout [24] $end
$var wire 1 S! acout [23] $end
$var wire 1 T! acout [22] $end
$var wire 1 U! acout [21] $end
$var wire 1 V! acout [20] $end
$var wire 1 W! acout [19] $end
$var wire 1 X! acout [18] $end
$var wire 1 Y! acout [17] $end
$var wire 1 Z! acout [16] $end
$var wire 1 [! acout [15] $end
$var wire 1 \! acout [14] $end
$var wire 1 ]! acout [13] $end
$var wire 1 ^! acout [12] $end
$var wire 1 _! acout [11] $end
$var wire 1 `! acout [10] $end
$var wire 1 a! acout [9] $end
$var wire 1 b! acout [8] $end
$var wire 1 c! acout [7] $end
$var wire 1 d! acout [6] $end
$var wire 1 e! acout [5] $end
$var wire 1 f! acout [4] $end
$var wire 1 g! acout [3] $end
$var wire 1 h! acout [2] $end
$var wire 1 i! acout [1] $end
$var wire 1 j! acout [0] $end
$var wire 1 k! alout [31] $end
$var wire 1 l! alout [30] $end
$var wire 1 m! alout [29] $end
$var wire 1 n! alout [28] $end
$var wire 1 o! alout [27] $end
$var wire 1 p! alout [26] $end
$var wire 1 q! alout [25] $end
$var wire 1 r! alout [24] $end
$var wire 1 s! alout [23] $end
$var wire 1 t! alout [22] $end
$var wire 1 u! alout [21] $end
$var wire 1 v! alout [20] $end
$var wire 1 w! alout [19] $end
$var wire 1 x! alout [18] $end
$var wire 1 y! alout [17] $end
$var wire 1 z! alout [16] $end
$var wire 1 {! alout [15] $end
$var wire 1 |! alout [14] $end
$var wire 1 }! alout [13] $end
$var wire 1 ~! alout [12] $end
$var wire 1 !" alout [11] $end
$var wire 1 "" alout [10] $end
$var wire 1 #" alout [9] $end
$var wire 1 $" alout [8] $end
$var wire 1 %" alout [7] $end
$var wire 1 &" alout [6] $end
$var wire 1 '" alout [5] $end
$var wire 1 (" alout [4] $end
$var wire 1 )" alout [3] $end
$var wire 1 *" alout [2] $end
$var wire 1 +" alout [1] $end
$var wire 1 ," alout [0] $end
$var wire 1 -" mrd $end
$var wire 1 ." ld_pc $end
$var wire 1 /" inc_pc $end
$var wire 1 0" ld_IR $end
$var wire 1 1" ldac $end
$var wire 1 2" ALU_setup $end
$var wire 1 3" mwr $end
$upscope $end
$upscope $end
$enddefinitions $end
#0
$dumpvars
x2!
x1!
x0!
x/!
x.!
x-!
x,!
x+!
x*!
x)!
x(!
x'!
x&!
x%!
x3!
xF!
x|
xu
x#!
xz
x!!
x}
xy
x$!
x"!
xx
xv
xw
x{
x~
xt
xG!
x5!
x4!
xj!
xZ!
xX!
xD!
xW!
xV!
xU!
x_!
x\!
xC!
xI!
x>!
xd!
xi!
x[!
xE!
x]!
xY!
xJ!
xg!
xA!
x?!
x<!
xH!
xh!
xf!
xe!
xa!
x@!
x;!
xc!
x`!
xb!
x^!
x=!
xB!
xr!
xq!
x&"
xQ!
xK!
x~!
xN!
xT!
x,"
x)"
x("
x#"
x{!
xM!
x$"
xP!
xO!
xz!
xy!
x*"
x!"
x|!
xx!
xR!
xw!
xu!
xt!
xs!
x+"
x'"
xv!
xS!
xL!
x%"
x""
x}!
0:
x0"
09
xn!
x/"
08
xm!
0?
x-"
0<
0;
07
xp!
xo!
xl!
x1"
x3"
0@
0>
xk!
x."
x2"
0=
0%
0$
0U
0.
0S
06
0+
03
0)
0-
0,
02
0&
0!
0_
0`
0(
0]
0Y
0W
0T
00
01
05
0*
0#
0"
0^
0\
0/
0'
04
0[
0Z
0X
0V
0o
0c
0k
0L
0b
0r
0R
0O
0I
0C
0A
0l
0P
0G
0B
0K
0J
0a
0q
0i
0m
0h
0g
0M
0p
0F
0f
0H
0j
0e
0d
0N
0Q
0D
0E
0n
x:!
x7!
x8!
x6!
1s
x9!
$end
#10000
02!
01!
00!
0/!
0.!
0-!
0,!
0+!
0*!
0)!
0(!
0'!
0&!
0%!
03!
0F!
0|
0u
0#!
0z
0!!
0}
0y
0$!
0"!
0x
0v
0w
0{
0~
0t
0G!
05!
04!
0j!
0Z!
0X!
0D!
0W!
0V!
0U!
0_!
0\!
0C!
0I!
0>!
0d!
0i!
0[!
0E!
0]!
0Y!
0J!
0g!
0A!
0?!
0<!
0H!
0h!
0f!
0e!
0a!
0@!
0;!
0c!
0`!
0b!
0^!
0=!
0B!
0Q!
0K!
0N!
0T!
0M!
0P!
0O!
0R!
0S!
0L!
1r
#20000
0r
0s
#30000
0r!
0q!
0&"
0~!
0,"
0)"
0("
0#"
0{!
0$"
0z!
0y!
0*"
0!"
0|!
0x!
0w!
0u!
0t!
0s!
0+"
0'"
0v!
0%"
0""
0}!
0n!
0m!
0p!
0o!
0l!
1>
0k!
1=
1_
1]
1^
1r
1q
1p
#40000
1?
0>
0r
#50000
00"
0/"
1-"
01"
03"
1@
1>
0."
02"
1r
#60000
0?
1<
0>
0=
0r
#70000
x2!
x1!
x0!
x/!
x.!
x-!
x,!
x+!
x*!
x)!
x(!
x'!
x&!
x%!
x3!
x|
xu
x#!
xz
x!!
x}
xy
x$!
x"!
xx
xv
xw
x{
x~
xt
x5!
x4!
0-"
0<
0@
1>
1."
1=
1r
#80000
1?
0>
0r
#90000
1/"
1@
1>
0."
1r
#100000
0?
1<
0>
0=
0r
#110000
10"
0/"
1r
#120000
0r
#130000
1I!
1J!
00"
11"
1r
#140000
0r
#150000
1j!
1f!
1r!
1q!
1&"
1~!
1("
1#"
1{!
1$"
1z!
1y!
1!"
1|!
1x!
1w!
1u!
1t!
1s!
1+"
1'"
1v!
1%"
1""
1}!
1n!
1m!
1p!
1o!
1l!
01"
1k!
12"
1r
#160000
0r
#170000
0r!
0q!
0&"
0~!
1,"
0("
0#"
0{!
0$"
0z!
0y!
0!"
0|!
0x!
0w!
0u!
0t!
0s!
0'"
0v!
0%"
0""
0}!
0n!
0m!
0p!
0o!
0l!
13"
0k!
02"
1r
#180000
0r
#190000
1r
#200000
0r
#210000
1-"
03"
1r
#220000
0r
#230000
02!
01!
00!
0/!
0.!
0-!
0,!
0+!
0*!
0)!
0(!
0'!
0&!
0%!
03!
0|
0u
0#!
0z
0!!
0}
0y
0$!
0"!
0x
0v
0w
0{
0~
0t
15!
14!
0-"
1."
1r
#240000
0r
#250000
1/"
0."
1r
#260000
0r
#270000
10"
0/"
1r
#280000
0r
#290000
00"
11"
1r
#300000
0r
#310000
01"
12"
1r
#320000
0r
#330000
13"
02"
1r
#340000
0r
#350000
1r
#360000
0r
#370000
1-"
03"
1r
#380000
0r
#390000
0-"
1."
1r
#400000
0r
#410000
1/"
0."
1r
#420000
0r
#430000
10"
0/"
1r
#440000
0r
#450000
00"
11"
1r
#460000
0r
#470000
01"
12"
1r
#480000
0r
#490000
13"
02"
1r
#500000
0r
#510000
1r
#520000
0r
#530000
1-"
03"
1r
#540000
0r
#550000
0-"
1."
1r
#560000
0r
#570000
1/"
0."
1r
#580000
0r
#590000
10"
0/"
1r
#600000
0r
#610000
00"
11"
1r
#620000
0r
#630000
01"
12"
1r
#640000
0r
#650000
13"
02"
1r
#660000
0r
#670000
1r
#680000
0r
#690000
1-"
03"
1r
#700000
0r
#710000
0-"
1."
1r
#720000
0r
#730000
1/"
0."
1r
#740000
0r
#750000
10"
0/"
1r
#760000
0r
#770000
00"
11"
1r
#780000
0r
#790000
01"
12"
1r
#800000
0r
#810000
13"
02"
1r
#820000
0r
#830000
1r
#840000
0r
#850000
1-"
03"
1r
#860000
0r
#870000
0-"
1."
1r
#880000
0r
#890000
1/"
0."
1r
#900000
0r
#910000
10"
0/"
1r
#920000
0r
#930000
00"
11"
1r
#940000
0r
#950000
01"
12"
1r
#960000
0r
#970000
13"
02"
1r
